tests/__init__.py
tests/test_description.py
tests/test_ipc.py
tests/test_tools.py
wipo_ipc/__init__.py
wipo_ipc/description.py
wipo_ipc/ipc.py
wipo_ipc/tools.py
wipo_ipc/data/all_ipc.csv
wipo_ipc-1.0.0.dist-info/LICENSE
wipo_ipc-1.0.0.dist-info/METADATA
wipo_ipc-1.0.0.dist-info/WHEEL
wipo_ipc-1.0.0.dist-info/top_level.txt
wipo_ipc-1.0.0.dist-info/RECORD
