Metadata-Version: 2.1
Name: wipo-ipc
Version: 1.0.0
Summary: A library to work with the International Patent Classification(IPC) from the World Intellectual Property Organization(WIPO)
Home-page: https://github.com/mateusrangel/wipo-ipc
Author: Mateus Rangel
Author-email: mateusmrangel@hotmail.com
License: UNKNOWN
Platform: UNKNOWN
Classifier: Programming Language :: Python :: 3
Classifier: License :: OSI Approved :: GNU General Public License v3 (GPLv3)
Classifier: Operating System :: OS Independent
Requires-Python: >=3.6
